ambition_form_validators/__init__.py
ambition_form_validators/apps.py
ambition_form_validators/constants.py
ambition_form_validators/models.py
ambition_form_validators/urls.py
ambition_form_validators/wsgi.py
ambition_form_validators/form_validators/__init__.py
ambition_form_validators/form_validators/amphotericin_missed_doses.py
ambition_form_validators/form_validators/blood_result.py
ambition_form_validators/form_validators/education.py
ambition_form_validators/form_validators/fluconazole_missed_doses.py
ambition_form_validators/form_validators/flucytosine_missed_doses.py
ambition_form_validators/form_validators/follow_up.py
ambition_form_validators/form_validators/lumbar_puncture_csf.py
ambition_form_validators/form_validators/medical_expenses.py
ambition_form_validators/form_validators/medical_expenses_two_detail.py
ambition_form_validators/form_validators/microbiology.py
ambition_form_validators/form_validators/missed_doses.py
ambition_form_validators/form_validators/pk_pd_crf.py
ambition_form_validators/form_validators/previous_opportunistic_infection.py
ambition_form_validators/form_validators/radiology.py
ambition_form_validators/form_validators/significant_diagnoses.py
ambition_form_validators/form_validators/subject_consent.py
ambition_form_validators/form_validators/subject_screening.py
ambition_form_validators/form_validators/week16.py
ambition_form_validators/form_validators/week2.py
ambition_form_validators/form_validators/week4.py
ambition_form_validators/form_validators/patient_history/__init__.py
ambition_form_validators/form_validators/patient_history/arv_treatment_and_monitoring.py
ambition_form_validators/form_validators/patient_history/patient_history_form_validator.py
ambition_form_validators/tests/__init__.py
ambition_form_validators/tests/models.py
ambition_form_validators/tests/test_blood_result_form_validator.py
ambition_form_validators/tests/test_education_validator.py
ambition_form_validators/tests/test_follow_up_form_validator.py
ambition_form_validators-0.1.45.dist-info/AUTHORS
ambition_form_validators-0.1.45.dist-info/LICENSE
ambition_form_validators-0.1.45.dist-info/METADATA
ambition_form_validators-0.1.45.dist-info/WHEEL
ambition_form_validators-0.1.45.dist-info/top_level.txt
ambition_form_validators-0.1.45.dist-info/RECORD
